qiskit_algorithms/VERSION.txt
qiskit_algorithms/__init__.py
qiskit_algorithms/algorithm_job.py
qiskit_algorithms/algorithm_result.py
qiskit_algorithms/exceptions.py
qiskit_algorithms/list_or_dict.py
qiskit_algorithms/observables_evaluator.py
qiskit_algorithms/variational_algorithm.py
qiskit_algorithms/version.py
qiskit_algorithms/amplitude_amplifiers/__init__.py
qiskit_algorithms/amplitude_amplifiers/amplification_problem.py
qiskit_algorithms/amplitude_amplifiers/amplitude_amplifier.py
qiskit_algorithms/amplitude_amplifiers/grover.py
qiskit_algorithms/amplitude_estimators/__init__.py
qiskit_algorithms/amplitude_estimators/ae.py
qiskit_algorithms/amplitude_estimators/ae_utils.py
qiskit_algorithms/amplitude_estimators/amplitude_estimator.py
qiskit_algorithms/amplitude_estimators/estimation_problem.py
qiskit_algorithms/amplitude_estimators/fae.py
qiskit_algorithms/amplitude_estimators/iae.py
qiskit_algorithms/amplitude_estimators/mlae.py
qiskit_algorithms/eigensolvers/__init__.py
qiskit_algorithms/eigensolvers/eigensolver.py
qiskit_algorithms/eigensolvers/numpy_eigensolver.py
qiskit_algorithms/eigensolvers/vqd.py
qiskit_algorithms/gradients/__init__.py
qiskit_algorithms/gradients/qfi.py
qiskit_algorithms/gradients/qfi_result.py
qiskit_algorithms/gradients/utils.py
qiskit_algorithms/gradients/base/__init__.py
qiskit_algorithms/gradients/base/base_estimator_gradient.py
qiskit_algorithms/gradients/base/base_qgt.py
qiskit_algorithms/gradients/base/base_sampler_gradient.py
qiskit_algorithms/gradients/base/estimator_gradient_result.py
qiskit_algorithms/gradients/base/qgt_result.py
qiskit_algorithms/gradients/base/sampler_gradient_result.py
qiskit_algorithms/gradients/finite_diff/__init__.py
qiskit_algorithms/gradients/finite_diff/finite_diff_estimator_gradient.py
qiskit_algorithms/gradients/finite_diff/finite_diff_sampler_gradient.py
qiskit_algorithms/gradients/lin_comb/__init__.py
qiskit_algorithms/gradients/lin_comb/lin_comb_estimator_gradient.py
qiskit_algorithms-0.3.0.dist-info/LICENSE.txt
qiskit_algorithms-0.3.0.dist-info/METADATA
qiskit_algorithms-0.3.0.dist-info/WHEEL
qiskit_algorithms-0.3.0.dist-info/top_level.txt
qiskit_algorithms-0.3.0.dist-info/RECORD
