Metadata-Version: 2.1
Name: qiskit-algorithms
Version: 0.3.0
Summary: Qiskit Algorithms: A library of quantum computing algorithms
Home-page: https://github.com/qiskit-community/qiskit-algorithms
Author: Qiskit Algorithms Development Team
Author-email: qiskit@us.ibm.com
License: Apache-2.0
Project-URL: Bug Tracker, https://github.com/qiskit-community/qiskit-algorithms/issues
Project-URL: Documentation, https://qiskit-community.github.io/qiskit-algorithms/
Project-URL: Source Code, https://github.com/qiskit-community/qiskit-algorithms
Keywords: qiskit sdk quantum algorithms
Classifier: Environment :: Console
Classifier: License :: OSI Approved :: Apache Software License
Classifier: Intended Audience :: Developers
Classifier: Intended Audience :: Science/Research
Classifier: Operating System :: Microsoft :: Windows
Classifier: Operating System :: MacOS
Classifier: Operating System :: POSIX :: Linux
Classifier: Programming Language :: Python :: 3 :: Only
Classifier: Programming Language :: Python :: 3.8
Classifier: Programming Language :: Python :: 3.9
Classifier: Programming Language :: Python :: 3.10
Classifier: Programming Language :: Python :: 3.11
Classifier: Programming Language :: Python :: 3.12
Classifier: Topic :: Scientific/Engineering
Requires-Python: >=3.8
License-File: LICENSE.txt
Requires-Dist: qiskit>=0.44
Requires-Dist: scipy>=1.4
Requires-Dist: numpy>=1.17
